README
setup.py
TracCAS.egg-info/PKG-INFO
TracCAS.egg-info/SOURCES.txt
TracCAS.egg-info/dependency_links.txt
TracCAS.egg-info/entry_points.txt
TracCAS.egg-info/requires.txt
TracCAS.egg-info/top_level.txt
traccas/__init__.py
traccas/pycas.py
traccas/traccas.py
