Metadata-Version: 1.0
Name: TracCAS
Version: 2.0.1
Summary: A modified authentication plugin to use the Yale CAS system.
Home-page: http://trac-hacks.org/wiki/TracCasPlugin
Author: Noah Kantrowitz
Author-email: noah@coderanger.net
License: BSD
Keywords: trac 0.11 plugin cas authentication
Platform: UNKNOWN
